{
  "dependencies": {
    "gitdepend": ">= 0.0.0"
  },
  "name": "git",
  "maintainer_email": "vladislav.mikhailov@gdev.biz",
  "attributes": {
  },
  "license": "Apache 2.0",
  "suggestions": {
  },
  "platforms": {
    "debian": ">= 0.0.0",
    "fedora": ">= 0.0.0",
    "centos": ">= 0.0.0",
    "amazon": ">= 0.0.0",
    "ubuntu": ">= 0.0.0",
    "redhat": ">= 0.0.0"
  },
  "maintainer": "Vladislav Mikhaylov",
  "long_description": "Description\n===========\nGets latest Git source tarball, configures & installs\n\nRequirements\n============\n- gcc\n- make/automake\n- openssl libs&headers\n- curl/tclcurl\n\n",
  "version": "0.7.0",
  "recommendations": {
  },
  "recipes": {
    "git": "Installs latest Git client"
  },
  "groupings": {
  },
  "conflicting": {
  },
  "replacing": {
  },
  "description": "Installs latest Git client",
  "providing": {
  }
}