{
  "dependencies": {
  },
  "name": "varnish",
  "maintainer_email": "cookbooks@opscode.com",
  "attributes": {
  },
  "license": "Apache 2.0",
  "suggestions": {
  },
  "platforms": {
    "debian": ">= 0.0.0",
    "ubuntu": ">= 0.0.0"
  },
  "maintainer": "Opscode, Inc.",
  "long_description": "",
  "version": "0.8.0",
  "recommendations": {
  },
  "recipes": {
    "varnish": "Installs and configures varnish"
  },
  "groupings": {
  },
  "conflicting": {
  },
  "replacing": {
  },
  "description": "Instsalls and configures varnish",
  "providing": {
  }
}